py_random_dot_org/__init__.py
py_random_dot_org/basic_api.py
py_random_dot_org-1.0.2.dist-info/LICENSE.txt
py_random_dot_org-1.0.2.dist-info/METADATA
py_random_dot_org-1.0.2.dist-info/WHEEL
py_random_dot_org-1.0.2.dist-info/top_level.txt
py_random_dot_org-1.0.2.dist-info/RECORD
