Metadata-Version: 2.1
Name: py-random-dot-org
Version: 1.0.2
Summary: Random.org Api Wrapped in Python
Author-email: Nick Seinsche <nick.seinsche@gmail.com>
License: Copyright (c) 2012-2024 Scott Chacon and others
Project-URL: Repository, https://github.com/Nick-Seinsche/py_random_dot_org
Project-URL: Documentation, https://nick-seinsche.github.io/py_random_dot_org/
Keywords: random,api,wrapper
Requires-Python: >=3.11
License-File: LICENSE.txt
Requires-Dist: requests
